msc_chart_generator/__init__.py
msc_chart_generator/generator.py
msc_chart_generator/msc_chart.py
msc_chart_generator-0.0.1.dist-info/LICENSE
msc_chart_generator-0.0.1.dist-info/METADATA
msc_chart_generator-0.0.1.dist-info/WHEEL
msc_chart_generator-0.0.1.dist-info/top_level.txt
msc_chart_generator-0.0.1.dist-info/RECORD
